LCNE_patchseq_analysis/__init__.py
LCNE_patchseq_analysis/data_util/__init__.py
LCNE_patchseq_analysis/data_util/mesh.py
LCNE_patchseq_analysis/data_util/metadata.py
LCNE_patchseq_analysis/data_util/nwb.py
LCNE_patchseq_analysis/efel/__init__.py
LCNE_patchseq_analysis/efel/core.py
LCNE_patchseq_analysis/efel/efel_per_spike_features.json
LCNE_patchseq_analysis/efel/io.py
LCNE_patchseq_analysis/efel/pipeline.py
LCNE_patchseq_analysis/efel/plot.py
LCNE_patchseq_analysis/efel/population.py
LCNE_patchseq_analysis/efel/util.py
LCNE_patchseq_analysis/figures/__init__.py
LCNE_patchseq_analysis/figures/fig_3a.py
LCNE_patchseq_analysis/figures/fig_3b.py
LCNE_patchseq_analysis/figures/fig_3c.py
LCNE_patchseq_analysis/figures/main_figure.py
LCNE_patchseq_analysis/figures/sup_figures.py
LCNE_patchseq_analysis/figures/util.py
LCNE_patchseq_analysis/pipeline_util/__init__.py
LCNE_patchseq_analysis/pipeline_util/ephys.py
LCNE_patchseq_analysis/pipeline_util/lims.py
LCNE_patchseq_analysis/pipeline_util/metadata.py
LCNE_patchseq_analysis/pipeline_util/s3.py
LCNE_patchseq_analysis/pipeline_util/sequencing.py
LCNE_patchseq_analysis/plot_util/swc.py
LCNE_patchseq_analysis/population_analysis/__init__.py
LCNE_patchseq_analysis/population_analysis/anova.py
LCNE_patchseq_analysis/population_analysis/filters.py
LCNE_patchseq_analysis/population_analysis/spikes.py
lcne_patchseq_analysis-0.28.0.dist-info/licenses/LICENSE
lcne_patchseq_analysis-0.28.0.dist-info/METADATA
lcne_patchseq_analysis-0.28.0.dist-info/WHEEL
lcne_patchseq_analysis-0.28.0.dist-info/top_level.txt
lcne_patchseq_analysis-0.28.0.dist-info/RECORD
