Metadata-Version: 2.4
Name: LCNE-patchseq-analysis
Version: 0.28.0
Summary: Generated from aind-library-template
Author: Allen Institute for Neural Dynamics
Author-email: Han Hou <han.hou@alleninstitute.org>
License: MIT
Classifier: Programming Language :: Python :: 3
Requires-Python: >=3.9
License-File: LICENSE
Requires-Dist: numpy
Requires-Dist: pandas
Requires-Dist: matplotlib
Requires-Dist: seaborn
Requires-Dist: h5py
Requires-Dist: s3fs
Requires-Dist: requests
Requires-Dist: trimesh
Requires-Dist: statsmodels
Provides-Extra: dev
Requires-Dist: black; extra == "dev"
Requires-Dist: coverage; extra == "dev"
Requires-Dist: flake8; extra == "dev"
Requires-Dist: interrogate; extra == "dev"
Requires-Dist: isort; extra == "dev"
Requires-Dist: Sphinx; extra == "dev"
Requires-Dist: furo; extra == "dev"
Provides-Extra: efel
Requires-Dist: efel; extra == "efel"
Requires-Dist: tables; extra == "efel"
Provides-Extra: panel
Requires-Dist: panel; extra == "panel"
Requires-Dist: watchfiles; extra == "panel"
Requires-Dist: s3fs; extra == "panel"
Requires-Dist: bokeh; extra == "panel"
Requires-Dist: umap-learn; extra == "panel"
Requires-Dist: tabulate; extra == "panel"
Provides-Extra: pipeline
Requires-Dist: black; extra == "pipeline"
Requires-Dist: coverage; extra == "pipeline"
Requires-Dist: flake8; extra == "pipeline"
Requires-Dist: interrogate; extra == "pipeline"
Requires-Dist: isort; extra == "pipeline"
Requires-Dist: Sphinx; extra == "pipeline"
Requires-Dist: furo; extra == "pipeline"
Requires-Dist: openpyxl; extra == "pipeline"
Requires-Dist: pg8000; extra == "pipeline"
Provides-Extra: all
Requires-Dist: black; extra == "all"
Requires-Dist: coverage; extra == "all"
Requires-Dist: flake8; extra == "all"
Requires-Dist: interrogate; extra == "all"
Requires-Dist: isort; extra == "all"
Requires-Dist: Sphinx; extra == "all"
Requires-Dist: furo; extra == "all"
Requires-Dist: panel; extra == "all"
Requires-Dist: watchfiles; extra == "all"
Requires-Dist: openpyxl; extra == "all"
Requires-Dist: pg8000; extra == "all"
Requires-Dist: efel; extra == "all"
Requires-Dist: bokeh; extra == "all"
Requires-Dist: h5py; extra == "all"
Requires-Dist: tqdm; extra == "all"
Requires-Dist: tables; extra == "all"
Requires-Dist: s3fs; extra == "all"
Dynamic: license-file
